{
    "/js/app.js": "/js/app.js",
    "/js/custom.min.js": "/js/custom.min.js",
    "/css/template.css": "/css/template.css",
    "/css/colors/blue-dark.css": "/css/colors/blue-dark.css",
    "/css/colors/blue.css": "/css/colors/blue.css",
    "/css/colors/default-dark.css": "/css/colors/default-dark.css",
    "/css/colors/default.css": "/css/colors/default.css",
    "/css/colors/green-dark.css": "/css/colors/green-dark.css",
    "/css/colors/green.css": "/css/colors/green.css",
    "/css/colors/megna-dark.css": "/css/colors/megna-dark.css",
    "/css/colors/megna.css": "/css/colors/megna.css",
    "/css/colors/purple-dark.css": "/css/colors/purple-dark.css",
    "/css/colors/purple.css": "/css/colors/purple.css",
    "/css/colors/red-dark.css": "/css/colors/red-dark.css",
    "/css/colors/red.css": "/css/colors/red.css",
    "/css/app.css": "/css/app.css",
    "/css/custom.css": "/css/custom.css",
    "/js/jquery.min.js": "/js/jquery.min.js",
    "/js/sidebarmenu.js": "/js/sidebarmenu.js",
    "/js/select2.min.js": "/js/select2.min.js",
    "/js/bootstrap-select.min.js": "/js/bootstrap-select.min.js",
    "/js/waves.js": "/js/waves.js",
    "/js/jquery.slimscroll.js": "/js/jquery.slimscroll.js",
    "/js/customMain.js": "/js/customMain.js",
    "/js/sticky-kit.min.js": "/js/sticky-kit.min.js",
    "/js/jquery.multi-select.js": "/js/jquery.multi-select.js",
    "/js/jquery.bootstrap-touchspin.min.js": "/js/jquery.bootstrap-touchspin.min.js",
    "/js/bootstrap-tagsinput.min.js": "/js/bootstrap-tagsinput.min.js",
    "/css/bootstrap-datepicker.min.css": "/css/bootstrap-datepicker.min.css",
    "/css/bootstrap-select.min.css": "/css/bootstrap-select.min.css",
    "/css/bootstrap-tagsinput.css": "/css/bootstrap-tagsinput.css",
    "/css/jquery.bootstrap-touchspin.min.css": "/css/jquery.bootstrap-touchspin.min.css",
    "/css/multi-select.css": "/css/multi-select.css",
    "/css/bootstrap.min.css": "/css/bootstrap.min.css",
    "/css/select2.min.css": "/css/select2.min.css"
}
